[
  {
      "delegateName": "liskit",
      "delegateAddress": "10310263204519541551L",
      "proposal": "https://forum.lisk.io/viewtopic.php?f=48&t=197",
      "githubUsername": "andreafspeziale",
      "poolPercentage": {
        "O": "80",
        "P": "20"
      },
      "affiliation": "GDT",
      "liskChat": "liskit.me",
      "pool": "http://liskit.me",
      "poolMember": false,
      "required": false,
      "featured": false
    },
    {
    "delegateName": "dakk",
    "delegateAddress": "2324852447570841050L",
    "proposal": "https://forum.lisk.io/viewtopic.php?f=48&t=1094",
    "githubUsername": "dakk",
    "poolPercentage": {
      "O": "80",
      "P": "20"
    },
    "affiliation": "GDT",
    "liskChat": "dakk_delegate",
    "pool": "https://dakk.github.io/lisk-pool/",
    "poolMember": false,
    "required": false,
    "featured": false
  },
  {
    "delegateName": "vekexasia",
    "delegateAddress": "9102643396261850794L",
    "proposal": "https://forum.lisk.io/viewtopic.php?f=48&t=1546",
    "githubUsername": "vekexasia",
    "poolPercentage": {
      "O": "75",
      "P": "25"
    },
    "affiliation": "GDT",
    "liskChat": "vekexasia",
    "pool": null,
    "poolMember": false,
    "required": false,
    "featured": false
  },
  {
    "delegateName": "5an1ty",
    "delegateAddress": "14871479939815286293L",
    "proposal": "https://forum.lisk.io/viewtopic.php?f=48&t=1521",
    "githubUsername": "5an1ty",
    "poolPercentage": {
      "P": "25",
      "D": "0",
      "O": "75"
    },
    "affiliation": "Freelance",
    "liskChat": "5an1ty",
    "pool": "https://pool.liskgdt.net",
    "poolMember": false,
    "required": false,
    "featured": true
  },
  {
    "delegateName": "cc001",
    "delegateAddress": "6787154358850114730L",
    "proposal": "https://forum.lisk.io/viewtopic.php?f=48&t=54",
    "githubUsername": "simonmorgenthaler",
    "poolPercentage": {
      "D": "25",
      "O": "75"
    },
    "affiliation": "GDT",
    "liskChat": "cc001",
    "pool": null,
    "poolMember": false,
    "required": false,
    "featured": false
  },
  {
    "delegateName": "atreides",
    "delegateAddress": "305922413481072012L",
    "proposal": "https://forum.lisk.io/viewtopic.php?f=48&t=350",
    "githubUsername": "stenea",
    "poolPercentage": {
      "P": "40",
      "D": "0",
      "O": "60"
    },
    "affiliation": "Freelance",
    "liskChat": "atreides",
    "pool": null,
    "poolMember": false,
    "required": false,
    "featured": false
  },
  {
    "delegateName": "gr33ndrag0n",
    "delegateAddress": "194109334904015388L",
    "proposal": "https://forum.lisk.io/viewtopic.php?f=48&t=143",
    "githubUsername": "Gr33nDrag0n69",
    "poolPercentage": {
      "O": "100"
    },
    "affiliation": "GDT",
    "liskChat": "Gr33ndrag0n",
    "pool": null,
    "poolMember": false,
    "required": false,
    "featured": false
  },
  {
    "delegateName": "mrv",
    "delegateAddress": "11380384760969655418L",
    "proposal": "https://forum.lisk.io/viewtopic.php?t=292",
    "githubUsername": "mrv777",
    "poolPercentage": {
      "P": "5",
      "D": "50",
      "O": "45"
    },
    "affiliation": "GDT",
    "liskChat": "MrV",
    "pool": "https://lisktools.io/profitShares.php",
    "poolMember": false,
    "required": false,
    "featured": false
  },
  {
    "delegateName": "wannabe_rotebaron",
    "delegateAddress": "16379340065696424247L",
    "proposal": "https://forum.lisk.io/viewtopic.php?t=1135",
    "githubUsername": "cezarsn",
    "poolPercentage": {
      "P": "40",
      "D": "0",
      "O": "60"
    },
    "affiliation": "Freelance",
    "liskChat": "wannabe_RoteBaron",
    "pool": null,
    "poolMember": false,
    "required": false,
    "featured": false
  },
  {
    "delegateName": "alepop",
    "delegateAddress": "9010579446607279905L",
    "proposal": "https://forum.lisk.io/viewtopic.php?t=1526",
    "githubUsername": "alepop",
    "poolPercentage": {
      "P": "40",
      "D": "0",
      "O": "60"
    },
    "affiliation": "Freelance",
    "liskChat": "alepop",
    "pool": null,
    "poolMember": false,
    "required": false,
    "featured": true
  },
  {
    "delegateName": "4fryn",
    "delegateAddress": "12632212355488748579L",
    "proposal": "https://forum.lisk.io/viewtopic.php?t=1560",
    "githubUsername": "4fryn",
    "poolPercentage": {
      "P": "80",
      "D": "15",
      "O": "5"
    },
    "affiliation": "Freelance",
    "liskChat": "4fryn",
    "pool": null,
    "poolMember": false,
    "required": false,
    "featured": false
  },
  {
    "delegateName": "carbonara",
    "delegateAddress": "6165534766664619667L",
    "proposal": "https://forum.lisk.io/viewtopic.php?t=1530",
    "githubUsername": "xunga",
    "poolPercentage": {
      "O": "100"
    },
    "affiliation": "Freelance",
    "liskChat": "carbonara",
    "pool": null,
    "poolMember": false,
    "required": false,
    "featured": true
  },
  {
    "delegateName": "liskpro.com",
    "delegateAddress": "13112651512533400586L",
    "proposal": "https://forum.lisk.io/viewtopic.php?f=48&t=1524",
    "githubUsername": "liskprocom",
    "poolPercentage": {
      "D": "85",
      "O": "15"
    },
    "affiliation": "Freelance",
    "liskChat": "LiskPro.com",
    "pool": null,
    "poolMember": false,
    "required": false,
    "featured": false
  },
  {
    "delegateName": "joo5ty",
    "delegateAddress": "12654423644480926777L",
    "proposal": "https://forum.lisk.io/viewtopic.php?f=48&t=1543",
    "githubUsername": "Joo5t",
    "poolPercentage": {
      "D": "25",
      "O": "75"
    },
    "affiliation": "Freelance",
    "liskChat": "joo5ty",
    "pool": null,
    "poolMember": false,
    "required": false,
    "featured": true
  },
  {
    "delegateName": "thepool",
    "delegateAddress": "10839494368003872009L",
    "proposal": "https://forum.lisk.io/viewtopic.php?f=48&t=1366",
    "githubUsername": "karek314",
    "poolPercentage": {
      "P": "70",
      "O": "30"
    },
    "affiliation": "Freelance",
    "liskChat": "Karek",
    "pool": "http://thepool.io/",
    "poolMember": false,
    "required": false,
    "featured": false
  },
  {
    "delegateName": "bioly",
    "delegateAddress": "7984234674117396356L",
    "proposal": "https://forum.lisk.io/viewtopic.php?f=48&t=237",
    "githubUsername": "biolypl",
    "poolPercentage": {
      "P": "25",
      "O": "75"
    },
    "affiliation": "GDT",
    "liskChat": "biolypl",
    "pool": "http://pool.mylisk.com/",
    "poolMember": false,
    "required": false,
    "featured": false
  },
  {
    "delegateName": "pelops",
    "delegateAddress": "6669300595452632273L",
    "proposal": "https://forum.lisk.io/viewtopic.php?f=48&t=1576",
    "githubUsername": "cb0",
    "poolPercentage": {
      "D": "90",
      "O": "10"
    },
    "affiliation": "Freelance",
    "liskChat": "cb0",
    "pool": null,
    "poolMember": false,
    "required": false,
    "featured": false
  }
]
